gwcs/__init__.py
gwcs/_version.py
gwcs/api.py
gwcs/examples.py
gwcs/extension.py
gwcs/fitswcs.py
gwcs/geometry.py
gwcs/region.py
gwcs/selector.py
gwcs/spectroscopy.py
gwcs/utils.py
gwcs/wcstools.py
gwcs/converters/__init__.py
gwcs/converters/geometry.py
gwcs/converters/selector.py
gwcs/converters/spectroscopy.py
gwcs/converters/wcs.py
gwcs/converters/tests/__init__.py
gwcs/converters/tests/test_selector.py
gwcs/converters/tests/test_transforms.py
gwcs/converters/tests/test_wcs.py
gwcs/coordinate_frames/__init__.py
gwcs/coordinate_frames/_base.py
gwcs/coordinate_frames/_celestial.py
gwcs/coordinate_frames/_composite.py
gwcs/coordinate_frames/_core.py
gwcs/coordinate_frames/_empty.py
gwcs/coordinate_frames/_frame.py
gwcs/coordinate_frames/_properties.py
gwcs/coordinate_frames/_spectral.py
gwcs/coordinate_frames/_stokes.py
gwcs/coordinate_frames/_temporal.py
gwcs/coordinate_frames/_utils.py
gwcs/tests/__init__.py
gwcs/tests/conftest.py
gwcs/tests/test_api.py
gwcs/tests/test_api_slicing.py
gwcs/tests/test_bounding_box.py
gwcs/tests/test_coordinate_systems.py
gwcs/tests/test_extension.py
gwcs/tests/test_geometry.py
gwcs/tests/test_region.py
gwcs/tests/test_spectroscopy_models.py
gwcs/tests/test_utils.py
gwcs/tests/test_wcs.py
gwcs/tests/utils.py
gwcs/tests/data/__init__.py
gwcs/tests/data/acs.hdr
gwcs/tests/data/acs_wfc.hdr
gwcs/tests/data/miri_lrs_wcs.asdf
gwcs/tests/data/miriwcs.asdf
gwcs/tests/data/nircamwcs.asdf
gwcs/tests/data/simple_wcs2.hdr
gwcs/tests/data/stokes.txt
gwcs/wcs/__init__.py
gwcs/wcs/_exception.py
gwcs/wcs/_pipeline.py
gwcs/wcs/_step.py
gwcs/wcs/_utils.py
gwcs/wcs/_wcs.py
gwcs-0.26.0.dist-info/licenses/licenses/LICENSE.rst
gwcs-0.26.0.dist-info/METADATA
gwcs-0.26.0.dist-info/WHEEL
gwcs-0.26.0.dist-info/entry_points.txt
gwcs-0.26.0.dist-info/top_level.txt
gwcs-0.26.0.dist-info/RECORD
