Metadata-Version: 2.4
Name: gwcs
Version: 0.26.0
Summary: Generalized World Coordinate System
Author-email: gwcs developers <help@stsci.edu>
Project-URL: Homepage, https://github.com/spacetelescope/gwcs
Project-URL: Tracker, https://github.com/spacetelescope/gwcs/issues
Project-URL: Documentation, https://gwcs.readthedocs.io/en/stable/
Project-URL: Source Code, https://github.com/spacetelescope/jwst
Requires-Python: >=3.11
License-File: licenses/LICENSE.rst
Requires-Dist: asdf>=3.3.0
Requires-Dist: astropy>=6.0
Requires-Dist: numpy>=1.25
Requires-Dist: scipy>=1.14.1
Requires-Dist: asdf_wcs_schemas>=0.5.0
Requires-Dist: asdf-astropy>=0.8.0
Provides-Extra: docs
Requires-Dist: sphinx; extra == "docs"
Requires-Dist: sphinx-automodapi; extra == "docs"
Requires-Dist: sphinx-astropy; extra == "docs"
Requires-Dist: sphinx-copybutton; extra == "docs"
Requires-Dist: sphinx-asdf; extra == "docs"
Requires-Dist: furo; extra == "docs"
Requires-Dist: sphinx-tabs; extra == "docs"
Requires-Dist: matplotlib; extra == "docs"
Provides-Extra: test
Requires-Dist: ci-watson>=0.3.0; extra == "test"
Requires-Dist: pytest>=8.0.0; extra == "test"
Requires-Dist: pytest-astropy>=0.11.0; extra == "test"
Dynamic: license-file
